{
  "transactionId" : "ec7fedd0-0125-4181-b746-1f4ec21a4f4a",
  "transaction" : {
    "transactionId" : "ec7fedd0-0125-4181-b746-1f4ec21a4f4a",
    "fromAccount" : "558692523873",
    "toAccount" : "808799342805",
    "amount" : 16017.03,
    "currency" : "EUR",
    "fromBankSwift" : "RABONL2U",
    "toBankSwift" : "ASBKNZ2A",
    "fromBankName" : "Rabobank",
    "toBankName" : "ASB Bank Limited",
    "timestamp" : "2025-06-17T14:05:19.732748",
    "status" : "PENDING",
    "fromIBAN" : "NL9030001184258539",
    "toIBAN" : "This country does not use IBAN",
    "fromCountryCode" : "NL",
    "toCountryCode" : "NZ"
  },
  "fraudDetectionResult" : {
    "transactionId" : "ec7fedd0-0125-4181-b746-1f4ec21a4f4a",
    "riskScore" : 70,
    "riskLevel" : "MEDIUM",
    "alerts" : [ {
      "alertId" : "31d46820-54c5-4e60-9b99-ab2fd3d00cb7",
      "fraudType" : "HIGH_AMOUNT_THRESHOLD",
      "description" : "High Amount Transaction",
      "severity" : 7,
      "details" : "Transaction amount 16017.03 exceeds threshold 15000.0",
      "timestamp" : "2025-06-17T15:53:38.631482",
      "status" : "ACTIVE"
    } ],
    "additionalData" : null,
    "detectionTimestamp" : "2025-06-17T15:53:38.631491",
    "fraudulent" : true
  },
  "reportGeneratedAt" : "2025-06-17T15:53:38.634883"
}