{
  "transactionId" : "a3862852-d430-4daa-b71d-2bd11a17773f",
  "transaction" : {
    "transactionId" : "a3862852-d430-4daa-b71d-2bd11a17773f",
    "fromAccount" : "856155196646",
    "toAccount" : "137710565505",
    "amount" : 404.54,
    "currency" : "EUR",
    "fromBankSwift" : "DEUTDEFF",
    "toBankSwift" : "AZBAAFKAXXX",
    "fromBankName" : "Deutsche Bank AG",
    "toBankName" : "Azizi Bank",
    "timestamp" : "2025-06-17T15:54:30.523706",
    "status" : "PENDING",
    "fromIBAN" : "DE76500700100921626754",
    "toIBAN" : "This country does not use IBAN",
    "fromCountryCode" : "DE",
    "toCountryCode" : "AF"
  },
  "fraudDetectionResult" : {
    "transactionId" : "a3862852-d430-4daa-b71d-2bd11a17773f",
    "riskScore" : 120,
    "riskLevel" : "LOW",
    "alerts" : [ {
      "alertId" : "b8e90a05-e091-4268-982e-d32908b6747e",
      "fraudType" : "CROSS_BORDER_HIGH_RISK",
      "description" : "Cross-Border High Risk",
      "severity" : 8,
      "details" : "Transaction involves high-risk country. From: DE, To: AF",
      "timestamp" : "2025-06-17T15:54:30.540456",
      "status" : "ACTIVE"
    }, {
      "alertId" : "2103b3be-4642-4dae-a4b6-fa79e3713a4b",
      "fraudType" : "FREQUENT_SMALL_AMOUNTS",
      "description" : "Frequent Small Amounts",
      "severity" : 4,
      "details" : "Small transaction amount 404.54 may indicate structuring behavior",
      "timestamp" : "2025-06-17T15:54:30.540518",
      "status" : "ACTIVE"
    } ],
    "additionalData" : null,
    "detectionTimestamp" : "2025-06-17T15:54:30.540545",
    "fraudulent" : true
  },
  "reportGeneratedAt" : "2025-06-17T15:54:30.557289"
}