{
  "transactionId" : "d9096b98-1624-47c9-b515-e7edcd924986",
  "transaction" : {
    "transactionId" : "d9096b98-1624-47c9-b515-e7edcd924986",
    "fromAccount" : "707999196040",
    "toAccount" : "290392433492",
    "amount" : 1191.54,
    "currency" : "AUD",
    "fromBankSwift" : "DEUTAU2S",
    "toBankSwift" : "BMOCCAMT",
    "fromBankName" : "Deutsche Bank AG",
    "toBankName" : "Bank of Montreal",
    "timestamp" : "2025-06-17T13:08:15.826936",
    "status" : "PENDING",
    "fromIBAN" : "This country does not use IBAN",
    "toIBAN" : "This country does not use IBAN",
    "fromCountryCode" : "AU",
    "toCountryCode" : "CA"
  },
  "fraudDetectionResult" : {
    "transactionId" : "d9096b98-1624-47c9-b515-e7edcd924986",
    "riskScore" : 0,
    "riskLevel" : "LOW",
    "alerts" : [ ],
    "additionalData" : null,
    "detectionTimestamp" : "2025-06-17T15:53:15.496242",
    "fraudulent" : false
  },
  "reportGeneratedAt" : "2025-06-17T15:53:15.498786"
}