{
  "transactionId" : "d3eb671e-c79a-4255-9d30-ec2d9150f42d",
  "transaction" : {
    "transactionId" : "d3eb671e-c79a-4255-9d30-ec2d9150f42d",
    "fromAccount" : "1298175947",
    "toAccount" : "499442179139",
    "amount" : 2831.36,
    "currency" : "EUR",
    "fromBankSwift" : "NBPLT21",
    "toBankSwift" : "UNCRITMM",
    "fromBankName" : "Šiaulių Bankas",
    "toBankName" : "UniCredit S.p.A.",
    "timestamp" : "2025-06-17T11:02:12.529539",
    "status" : "PROCESSING",
    "fromIBAN" : "LT197300001045839795",
    "toIBAN" : "IT9102008000000000021628158",
    "fromCountryCode" : "LT",
    "toCountryCode" : "IT"
  },
  "fraudDetectionResult" : {
    "transactionId" : "d3eb671e-c79a-4255-9d30-ec2d9150f42d",
    "riskScore" : 0,
    "riskLevel" : "LOW",
    "alerts" : [ ],
    "additionalData" : null,
    "detectionTimestamp" : "2025-06-17T15:53:17.999865",
    "fraudulent" : false
  },
  "reportGeneratedAt" : "2025-06-17T15:53:18.003018"
}