{
  "transactionId" : "9dea79a1-11b4-4d7a-9a85-dc6d98d66815",
  "transaction" : {
    "transactionId" : "9dea79a1-11b4-4d7a-9a85-dc6d98d66815",
    "fromAccount" : "045673153776",
    "toAccount" : "3662242851",
    "amount" : 47094.93,
    "currency" : "BRL",
    "fromBankSwift" : "BSCHBRSP",
    "toBankSwift" : "MELIIRTH",
    "fromBankName" : "Santander Brasil",
    "toBankName" : "Bank Melli Iran",
    "timestamp" : "2025-06-17T14:04:39.73296",
    "status" : "PROCESSING",
    "fromIBAN" : "BR75904008880001153044248",
    "toIBAN" : "This country does not use IBAN",
    "fromCountryCode" : "BR",
    "toCountryCode" : "IR"
  },
  "fraudDetectionResult" : {
    "transactionId" : "9dea79a1-11b4-4d7a-9a85-dc6d98d66815",
    "riskScore" : 150,
    "riskLevel" : "LOW",
    "alerts" : [ {
      "alertId" : "2ae73216-1e8e-4dd7-afcd-225da44056ea",
      "fraudType" : "CROSS_BORDER_HIGH_RISK",
      "description" : "Cross-Border High Risk",
      "severity" : 8,
      "details" : "Transaction involves high-risk country. From: BR, To: IR",
      "timestamp" : "2025-06-17T15:53:38.581862",
      "status" : "ACTIVE"
    }, {
      "alertId" : "2c343cde-1d94-42ff-a143-44f9b42a0921",
      "fraudType" : "HIGH_AMOUNT_THRESHOLD",
      "description" : "High Amount Transaction",
      "severity" : 7,
      "details" : "Transaction amount 47094.93 exceeds threshold 15000.0",
      "timestamp" : "2025-06-17T15:53:38.58192",
      "status" : "ACTIVE"
    } ],
    "additionalData" : null,
    "detectionTimestamp" : "2025-06-17T15:53:38.581928",
    "fraudulent" : true
  },
  "reportGeneratedAt" : "2025-06-17T15:53:38.586219"
}