{
  "transactionId" : "98f748bf-f9a7-42e5-be4d-a6a992a4614d",
  "transaction" : {
    "transactionId" : "98f748bf-f9a7-42e5-be4d-a6a992a4614d",
    "fromAccount" : "5372690077",
    "toAccount" : "747669359150",
    "amount" : 77256.43,
    "currency" : "CNY",
    "fromBankSwift" : "CIBKCNBJ",
    "toBankSwift" : "UBSWCHZH80A",
    "fromBankName" : "China CITIC Bank",
    "toBankName" : "UBS Switzerland AG",
    "timestamp" : "2025-06-15T08:51:51.426591",
    "status" : "FAILED",
    "fromIBAN" : "This country does not use IBAN",
    "toIBAN" : "CH1524300001297816556",
    "fromCountryCode" : "CN",
    "toCountryCode" : "CH"
  },
  "fraudDetectionResult" : {
    "transactionId" : "98f748bf-f9a7-42e5-be4d-a6a992a4614d",
    "riskScore" : 70,
    "riskLevel" : "MEDIUM",
    "alerts" : [ {
      "alertId" : "b857a38c-7713-421a-9815-c01b09ee7457",
      "fraudType" : "HIGH_AMOUNT_THRESHOLD",
      "description" : "High Amount Transaction",
      "severity" : 7,
      "details" : "Transaction amount 77256.43 exceeds threshold 15000.0",
      "timestamp" : "2025-06-17T15:53:34.817042",
      "status" : "ACTIVE"
    } ],
    "additionalData" : null,
    "detectionTimestamp" : "2025-06-17T15:53:34.817056",
    "fraudulent" : true
  },
  "reportGeneratedAt" : "2025-06-17T15:53:34.820747"
}