{
  "transactionId" : "bf01bb3b-7c07-49c6-bd5d-25dda0be36b4",
  "transaction" : {
    "transactionId" : "bf01bb3b-7c07-49c6-bd5d-25dda0be36b4",
    "fromAccount" : "697220158116",
    "toAccount" : "0372256801",
    "amount" : 772.59,
    "currency" : "SGD",
    "fromBankSwift" : "DBSBSGSG",
    "toBankSwift" : "HSBCNZ2A",
    "fromBankName" : "DBS Bank",
    "toBankName" : "HSBC New Zealand",
    "timestamp" : "2025-06-13T15:48:09.205701",
    "status" : "PENDING",
    "fromIBAN" : "This country does not use IBAN",
    "toIBAN" : "This country does not use IBAN",
    "fromCountryCode" : "SG",
    "toCountryCode" : "NZ"
  },
  "fraudDetectionResult" : {
    "transactionId" : "bf01bb3b-7c07-49c6-bd5d-25dda0be36b4",
    "riskScore" : 40,
    "riskLevel" : "MEDIUM",
    "alerts" : [ {
      "alertId" : "e79064a0-45a9-4640-9348-d381ebacd102",
      "fraudType" : "FREQUENT_SMALL_AMOUNTS",
      "description" : "Frequent Small Amounts",
      "severity" : 4,
      "details" : "Small transaction amount 772.59 may indicate structuring behavior",
      "timestamp" : "2025-06-17T15:53:34.062669",
      "status" : "ACTIVE"
    } ],
    "additionalData" : null,
    "detectionTimestamp" : "2025-06-17T15:53:34.062688",
    "fraudulent" : false
  },
  "reportGeneratedAt" : "2025-06-17T15:53:34.069146"
}