{
  "transactionId" : "6e9c3ef9-4564-4e78-8587-910431e79ef1",
  "transaction" : {
    "transactionId" : "6e9c3ef9-4564-4e78-8587-910431e79ef1",
    "fromAccount" : "9347969160",
    "toAccount" : "5763826117",
    "amount" : 51204.99,
    "currency" : "BEL",
    "fromBankSwift" : "KREDBEBB",
    "toBankSwift" : "NBPLT21",
    "fromBankName" : "KBC Bank N.V.",
    "toBankName" : "Šiaulių Bankas",
    "timestamp" : "2025-06-17T13:06:25.840033",
    "status" : "PROCESSING",
    "fromIBAN" : "BE62733000834548",
    "toIBAN" : "LT837300001135529402",
    "fromCountryCode" : "BE",
    "toCountryCode" : "LT"
  },
  "fraudDetectionResult" : {
    "transactionId" : "6e9c3ef9-4564-4e78-8587-910431e79ef1",
    "riskScore" : 70,
    "riskLevel" : "MEDIUM",
    "alerts" : [ {
      "alertId" : "b0ea4b87-3238-4e60-afbf-d60d6a5634b6",
      "fraudType" : "HIGH_AMOUNT_THRESHOLD",
      "description" : "High Amount Transaction",
      "severity" : 7,
      "details" : "Transaction amount 51204.99 exceeds threshold 15000.0",
      "timestamp" : "2025-06-17T15:53:36.909243",
      "status" : "ACTIVE"
    } ],
    "additionalData" : null,
    "detectionTimestamp" : "2025-06-17T15:53:36.909251",
    "fraudulent" : true
  },
  "reportGeneratedAt" : "2025-06-17T15:53:36.912651"
}