{
  "transactionId" : "6c10b7a9-79fd-4c8b-91c1-2e9722f050de",
  "transaction" : {
    "transactionId" : "6c10b7a9-79fd-4c8b-91c1-2e9722f050de",
    "fromAccount" : "649897040434",
    "toAccount" : "2808525909",
    "amount" : 989.43,
    "currency" : "SYP",
    "fromBankSwift" : "CBSYSYMM",
    "toBankSwift" : "LLOYGB2L",
    "fromBankName" : "Central Bank of Syria",
    "toBankName" : "Lloyds Bank",
    "timestamp" : "2025-06-16T22:44:20.565057",
    "status" : "PENDING",
    "fromIBAN" : "This country does not use IBAN",
    "toIBAN" : "GB85300000001892670440",
    "fromCountryCode" : "SY",
    "toCountryCode" : "GB"
  },
  "fraudDetectionResult" : {
    "transactionId" : "6c10b7a9-79fd-4c8b-91c1-2e9722f050de",
    "riskScore" : 120,
    "riskLevel" : "LOW",
    "alerts" : [ {
      "alertId" : "e0e7556a-60d7-44b7-ade2-72cfe902d518",
      "fraudType" : "CROSS_BORDER_HIGH_RISK",
      "description" : "Cross-Border High Risk",
      "severity" : 8,
      "details" : "Transaction involves high-risk country. From: SY, To: GB",
      "timestamp" : "2025-06-17T15:53:14.361533",
      "status" : "ACTIVE"
    }, {
      "alertId" : "06284025-8d93-4b00-a64c-8eb6d155f7bf",
      "fraudType" : "FREQUENT_SMALL_AMOUNTS",
      "description" : "Frequent Small Amounts",
      "severity" : 4,
      "details" : "Small transaction amount 989.43 may indicate structuring behavior",
      "timestamp" : "2025-06-17T15:53:14.361548",
      "status" : "ACTIVE"
    } ],
    "additionalData" : null,
    "detectionTimestamp" : "2025-06-17T15:53:14.361554",
    "fraudulent" : true
  },
  "reportGeneratedAt" : "2025-06-17T15:53:14.362434"
}