{
  "transactionId" : "068204b1-a428-4703-b92c-6bf68ac0c3fa",
  "transaction" : {
    "transactionId" : "068204b1-a428-4703-b92c-6bf68ac0c3fa",
    "fromAccount" : "867007252749",
    "toAccount" : "859419710726",
    "amount" : 6880.78,
    "currency" : "AFN",
    "fromBankSwift" : "GHBKAFKA",
    "toBankSwift" : "BCEELULL",
    "fromBankName" : "Ghazanfar Bank",
    "toBankName" : "BCEE",
    "timestamp" : "2025-06-17T14:05:49.72982",
    "status" : "PROCESSING",
    "fromIBAN" : "This country does not use IBAN",
    "toIBAN" : "LU640010000242639717",
    "fromCountryCode" : "AF",
    "toCountryCode" : "LU"
  },
  "fraudDetectionResult" : {
    "transactionId" : "068204b1-a428-4703-b92c-6bf68ac0c3fa",
    "riskScore" : 80,
    "riskLevel" : "HIGH",
    "alerts" : [ {
      "alertId" : "16c2a7f1-4ba8-4035-8148-59705a897df3",
      "fraudType" : "CROSS_BORDER_HIGH_RISK",
      "description" : "Cross-Border High Risk",
      "severity" : 8,
      "details" : "Transaction involves high-risk country. From: AF, To: LU",
      "timestamp" : "2025-06-17T15:53:38.668997",
      "status" : "ACTIVE"
    } ],
    "additionalData" : null,
    "detectionTimestamp" : "2025-06-17T15:53:38.66901",
    "fraudulent" : true
  },
  "reportGeneratedAt" : "2025-06-17T15:53:38.672302"
}