{
  "transactionId" : "f62f3eea-79e2-4cb0-b672-5d8d28777833",
  "transaction" : {
    "transactionId" : "f62f3eea-79e2-4cb0-b672-5d8d28777833",
    "fromAccount" : "5352881375",
    "toAccount" : "787148482736",
    "amount" : 27494.79,
    "currency" : "AFN",
    "fromBankSwift" : "GHBKAFKA",
    "toBankSwift" : "BOFMCAM2XXX",
    "fromBankName" : "Ghazanfar Bank",
    "toBankName" : "Bank of Montreal",
    "timestamp" : "2025-06-17T14:01:59.735545",
    "status" : "PENDING",
    "fromIBAN" : "This country does not use IBAN",
    "toIBAN" : "This country does not use IBAN",
    "fromCountryCode" : "AF",
    "toCountryCode" : "CA"
  },
  "fraudDetectionResult" : {
    "transactionId" : "f62f3eea-79e2-4cb0-b672-5d8d28777833",
    "riskScore" : 150,
    "riskLevel" : "LOW",
    "alerts" : [ {
      "alertId" : "5e036eae-6c3e-48dc-b096-c462f8c4c349",
      "fraudType" : "CROSS_BORDER_HIGH_RISK",
      "description" : "Cross-Border High Risk",
      "severity" : 8,
      "details" : "Transaction involves high-risk country. From: AF, To: CA",
      "timestamp" : "2025-06-17T15:53:15.841471",
      "status" : "ACTIVE"
    }, {
      "alertId" : "06ad6b8e-b0bf-4c6a-b2ea-85a6483d0d28",
      "fraudType" : "HIGH_AMOUNT_THRESHOLD",
      "description" : "High Amount Transaction",
      "severity" : 7,
      "details" : "Transaction amount 27494.79 exceeds threshold 15000.0",
      "timestamp" : "2025-06-17T15:53:15.841489",
      "status" : "ACTIVE"
    } ],
    "additionalData" : null,
    "detectionTimestamp" : "2025-06-17T15:53:15.841495",
    "fraudulent" : true
  },
  "reportGeneratedAt" : "2025-06-17T15:53:15.84317"
}