{
  "transactionId" : "c492af37-117e-4834-8fa1-be1ae16f29ff",
  "transaction" : {
    "transactionId" : "c492af37-117e-4834-8fa1-be1ae16f29ff",
    "fromAccount" : "444791103818",
    "toAccount" : "3594311494",
    "amount" : 79.96,
    "currency" : "AUD",
    "fromBankSwift" : "WESTPAC",
    "toBankSwift" : "BOFMCAM2XXX",
    "fromBankName" : "Westpac Banking Corp",
    "toBankName" : "Bank of Montreal",
    "timestamp" : "2025-06-17T13:56:44.737744",
    "status" : "PROCESSING",
    "fromIBAN" : "This country does not use IBAN",
    "toIBAN" : "This country does not use IBAN",
    "fromCountryCode" : "AU",
    "toCountryCode" : "CA"
  },
  "fraudDetectionResult" : {
    "transactionId" : "c492af37-117e-4834-8fa1-be1ae16f29ff",
    "riskScore" : 40,
    "riskLevel" : "MEDIUM",
    "alerts" : [ {
      "alertId" : "2665cef5-f9e7-4d0c-9a8d-9158446b0611",
      "fraudType" : "FREQUENT_SMALL_AMOUNTS",
      "description" : "Frequent Small Amounts",
      "severity" : 4,
      "details" : "Small transaction amount 79.96 may indicate structuring behavior",
      "timestamp" : "2025-06-17T15:53:37.975268",
      "status" : "ACTIVE"
    } ],
    "additionalData" : null,
    "detectionTimestamp" : "2025-06-17T15:53:37.975278",
    "fraudulent" : false
  },
  "reportGeneratedAt" : "2025-06-17T15:53:37.97982"
}