{
  "transactionId" : "69717d06-62fe-4a44-b0cc-b02771dc3ad2",
  "transaction" : {
    "transactionId" : "69717d06-62fe-4a44-b0cc-b02771dc3ad2",
    "fromAccount" : "293393284203",
    "toAccount" : "613510989553",
    "amount" : 844.04,
    "currency" : "GBP",
    "fromBankSwift" : "HSBCGB2L",
    "toBankSwift" : "HKBCCATT",
    "fromBankName" : "HSBC UK",
    "toBankName" : "Hongkong and Shanghai Banking Corp",
    "timestamp" : "2025-06-17T10:49:10.93846",
    "status" : "PENDING",
    "fromIBAN" : "GB43404404000547200056",
    "toIBAN" : "This country does not use IBAN",
    "fromCountryCode" : "GB",
    "toCountryCode" : "CA"
  },
  "fraudDetectionResult" : {
    "transactionId" : "69717d06-62fe-4a44-b0cc-b02771dc3ad2",
    "riskScore" : 40,
    "riskLevel" : "MEDIUM",
    "alerts" : [ {
      "alertId" : "fb184207-7d52-4167-8d09-581e87fb971c",
      "fraudType" : "FREQUENT_SMALL_AMOUNTS",
      "description" : "Frequent Small Amounts",
      "severity" : 4,
      "details" : "Small transaction amount 844.04 may indicate structuring behavior",
      "timestamp" : "2025-06-17T15:53:36.391424",
      "status" : "ACTIVE"
    } ],
    "additionalData" : null,
    "detectionTimestamp" : "2025-06-17T15:53:36.391434",
    "fraudulent" : false
  },
  "reportGeneratedAt" : "2025-06-17T15:53:36.396214"
}