{
  "transactionId" : "99b086c6-f41b-4387-864e-2802a0bff416",
  "transaction" : {
    "transactionId" : "99b086c6-f41b-4387-864e-2802a0bff416",
    "fromAccount" : "6209278381",
    "toAccount" : "1953496194",
    "amount" : 17256.34,
    "currency" : "CAD",
    "fromBankSwift" : "BOFMCAM2",
    "toBankSwift" : "EBILAEADXXX",
    "fromBankName" : "Bank of Montreal",
    "toBankName" : "Emirates NBD Bank",
    "timestamp" : "2025-06-17T11:02:52.527348",
    "status" : "PENDING",
    "fromIBAN" : "This country does not use IBAN",
    "toIBAN" : "This country does not use IBAN",
    "fromCountryCode" : "CA",
    "toCountryCode" : "AE"
  },
  "fraudDetectionResult" : {
    "transactionId" : "99b086c6-f41b-4387-864e-2802a0bff416",
    "riskScore" : 70,
    "riskLevel" : "MEDIUM",
    "alerts" : [ {
      "alertId" : "5b859ee1-9f9e-460e-8e20-c0467f94f07d",
      "fraudType" : "HIGH_AMOUNT_THRESHOLD",
      "description" : "High Amount Transaction",
      "severity" : 7,
      "details" : "Transaction amount 17256.34 exceeds threshold 15000.0",
      "timestamp" : "2025-06-17T15:53:23.197903",
      "status" : "ACTIVE"
    } ],
    "additionalData" : null,
    "detectionTimestamp" : "2025-06-17T15:53:23.197911",
    "fraudulent" : true
  },
  "reportGeneratedAt" : "2025-06-17T15:53:23.201211"
}