{
  "transactionId" : "645e9f11-78a3-4283-8553-ec61b68b34b0",
  "transaction" : {
    "transactionId" : "645e9f11-78a3-4283-8553-ec61b68b34b0",
    "fromAccount" : "003803883099",
    "toAccount" : "697652247669",
    "amount" : 2000,
    "currency" : "GBP",
    "fromBankSwift" : "BARCGB22",
    "toBankSwift" : "BNPAFRPP",
    "fromBankName" : "Barclays",
    "toBankName" : "BNP Paribas",
    "timestamp" : "2025-06-18T22:06:21.821119",
    "status" : "PROCESSING",
    "fromIBAN" : "GB50203002000593690523",
    "toIBAN" : "FR6130004000000001216730397",
    "fromCountryCode" : "GB",
    "toCountryCode" : "FR"
  },
  "fraudDetectionResult" : {
    "transactionId" : "645e9f11-78a3-4283-8553-ec61b68b34b0",
    "riskScore" : 40,
    "riskLevel" : "MEDIUM",
    "alerts" : [ {
      "alertId" : "a44a4ab3-3b9e-494c-b56e-4102f8401eca",
      "fraudType" : "ROUND_AMOUNT_PATTERN",
      "description" : "Round Amount Pattern",
      "severity" : 4,
      "details" : "Transaction amount 2000 follows suspicious round pattern",
      "timestamp" : "2025-06-18T22:10:44.370493",
      "status" : "ACTIVE"
    } ],
    "additionalData" : null,
    "detectionTimestamp" : "2025-06-18T22:10:44.3705",
    "fraudulent" : false
  },
  "reportGeneratedAt" : "2025-06-18T22:10:44.370894"
}