{
  "transactionId" : "75aedb97-57d2-4f8c-9406-32fed59048cc",
  "transaction" : {
    "transactionId" : "75aedb97-57d2-4f8c-9406-32fed59048cc",
    "fromAccount" : "0843558354",
    "toAccount" : "6605494372",
    "amount" : 64307.35,
    "currency" : "CAD",
    "fromBankSwift" : "BOFMCAM2",
    "toBankSwift" : "KREDBEBB",
    "fromBankName" : "Bank of Montreal",
    "toBankName" : "KBC Bank N.V.",
    "timestamp" : "2025-06-18T21:03:00.068487",
    "status" : "PROCESSING",
    "fromIBAN" : "This country does not use IBAN",
    "toIBAN" : "BE97733000526428",
    "fromCountryCode" : "CA",
    "toCountryCode" : "BE"
  },
  "fraudDetectionResult" : {
    "transactionId" : "75aedb97-57d2-4f8c-9406-32fed59048cc",
    "riskScore" : 70,
    "riskLevel" : "MEDIUM",
    "alerts" : [ {
      "alertId" : "323a9373-f58a-4473-bf5e-1ed0e8d41559",
      "fraudType" : "HIGH_AMOUNT_THRESHOLD",
      "description" : "High Amount Transaction",
      "severity" : 7,
      "details" : "Transaction amount 64307.35 exceeds threshold 15000.0",
      "timestamp" : "2025-06-18T21:06:52.508639",
      "status" : "ACTIVE"
    } ],
    "additionalData" : null,
    "detectionTimestamp" : "2025-06-18T21:06:52.508653",
    "fraudulent" : true
  },
  "reportGeneratedAt" : "2025-06-18T21:06:52.509125"
}